nwslpy/__init__.py
nwslpy/nwslpy.py
nwslpy/test_nwslpy.py
nwslpy-0.0.0.7000.dist-info/METADATA
nwslpy-0.0.0.7000.dist-info/WHEEL
nwslpy-0.0.0.7000.dist-info/licenses/LICENSE
nwslpy-0.0.0.7000.dist-info/RECORD
