Metadata-Version: 2.1
Name: nwslpy
Version: 0.0.0.7000
Summary: Python wrapper around the nwslR library
Project-URL: Homepage, https://github.com/nwslR/nwslpy
Project-URL: Bug Tracker, https://github.com/nwslR/nwslpy/issues
Author-email: Alison Gale <agale123.dev@gmail.com>
License-File: LICENSE
Classifier: License :: OSI Approved :: MIT License
Classifier: Operating System :: OS Independent
Classifier: Programming Language :: Python :: 3
Requires-Python: >=3.7
Requires-Dist: pandas
